delft/__init__.py
delft/applications/__init__.py
delft/applications/citationClassifier.py
delft/applications/citationClassifierV.py
delft/applications/citationIntentClassifier.py
delft/applications/dataseerClassifier.py
delft/applications/datasetTagger.py
delft/applications/grobidTagger.py
delft/applications/grobidTest.py
delft/applications/insultTagger.py
delft/applications/nerTagger.py
delft/applications/relationExtractor.py
delft/applications/softwareClassifier.py
delft/applications/softwareContextClassifier.py
delft/applications/toxicCommentClassifier.py
delft/sequenceLabelling/__init__.py
delft/sequenceLabelling/config.py
delft/sequenceLabelling/data_generator.py
delft/sequenceLabelling/evaluation.py
delft/sequenceLabelling/models.py
delft/sequenceLabelling/preprocess.py
delft/sequenceLabelling/reader.py
delft/sequenceLabelling/tagger.py
delft/sequenceLabelling/trainer.py
delft/sequenceLabelling/wrapper.py
delft/textClassification/__init__.py
delft/textClassification/config.py
delft/textClassification/data_generator.py
delft/textClassification/models.py
delft/textClassification/preprocess.py
delft/textClassification/reader.py
delft/textClassification/wrapper.py
delft/utilities/Attention.py
delft/utilities/Embeddings.py
delft/utilities/Tokenizer.py
delft/utilities/Transformer.py
delft/utilities/Utilities.py
delft/utilities/__init__.py
delft/utilities/crf_layer.py
delft/utilities/crf_wrapper_default.py
delft/utilities/crf_wrapper_for_bert.py
delft/utilities/layers.py
delft/utilities/misc.py
delft/utilities/numpy.py
delft/utilities/truecase_conll2003.py
delft/utilities/bert/__init__.py
delft/utilities/bert/create_pretraining_data.py
delft/utilities/bert/extract_features.py
delft/utilities/bert/modeling.py
delft/utilities/bert/modeling_test.py
delft/utilities/bert/optimization.py
delft/utilities/bert/optimization_test.py
delft/utilities/bert/run_classifier.py
delft/utilities/bert/run_classifier_delft.py
delft/utilities/bert/run_classifier_with_tfhub.py
delft-0.3.4.dist-info/LICENSE.txt
delft-0.3.4.dist-info/METADATA
delft-0.3.4.dist-info/WHEEL
delft-0.3.4.dist-info/top_level.txt
delft-0.3.4.dist-info/RECORD
