Metadata-Version: 2.1
Name: delft
Version: 0.3.4
Summary: a Deep Learning Framework for Text
Home-page: https://github.com/kermitt2/delft
Author: Patrice Lopez
Author-email: patrice.lopez@science-miner.com
License: UNKNOWN
Platform: UNKNOWN
Classifier: Programming Language :: Python :: 3.8
Classifier: License :: OSI Approved :: Apache Software License
Classifier: Operating System :: OS Independent
Requires-Python: >=3.7
Requires-Dist: accelerate (>=0.20.3)
Requires-Dist: h5py (==3.6.0)
Requires-Dist: lmdb (==1.2.1)
Requires-Dist: numpy (==1.22.3)
Requires-Dist: pandas (==1.3.5)
Requires-Dist: pydot (==1.4.0)
Requires-Dist: pytest
Requires-Dist: regex (==2021.11.10)
Requires-Dist: requests (>=2.20)
Requires-Dist: scikit-learn (==1.0.1)
Requires-Dist: tensorflow-addons (==0.19.0)
Requires-Dist: tensorflow (==2.9.3)
Requires-Dist: torch (==1.10.1)
Requires-Dist: tqdm (==4.62.3)
Requires-Dist: transformers (==4.33.2)
Requires-Dist: truecase
Requires-Dist: unidecode (==1.3.2)
